{
  "users": [
    {
      "id": 1765622420176,
      "username": "FUAT",
      "password": "1453",
      "email": "fuat1453@gmail.com",
      "phone": "5535535353",
      "birthDate": "2005-01-04",
      "gender": "Erkek",
      "isAdmin": false,
      "isOnline": true,
      "favorites": [],
      "alarmCount": 0
    },
    {
      "id": 1765636086458,
      "username": "AA",
      "password": "1234",
      "email": "B@C.D",
      "phone": "5555555555",
      "birthDate": "2001-01-01",
      "gender": "Erkek",
      "isAdmin": false,
      "isOnline": false,
      "favorites": [],
      "alarmCount": 0
    }
  ],
  "favorites": {
    "FUAT": [
      "DOGEUSDT",
      "DOTUSDT",
      "BTCUSDT",
      "ETHUSDT",
      "SOLUSDT"
    ],
    "DEMİR": [
      "SI=F",
      "BTCUSDT"
    ],
    "ENES": [],
    "SALİH": [
      "BTCUSDT",
      "ETHUSDT"
    ]
  },
  "alarms": [
    {
      "id": 1765281175097,
      "username": "FUAT",
      "symbol": "BTCUSDT",
      "targetPrice": 150790.99500107332,
      "direction": "UP",
      "note": ""
    }
  ],
  "supportMessages": [
    {
      "id": 1765641662868,
      "username": "AA",
      "contactInfo": null,
      "subject": "Öneri",
      "message": "A",
      "date": "13.12.2025 19:01:02",
      "isRead": false,
      "replies": [
        {
          "text": "B",
          "date": "13.12.2025 19:01:12"
        }
      ]
    },
    {
      "id": 1765620719610,
      "username": "Salih",
      "contactInfo": "salihaa",
      "subject": "Giriş Sorunu",
      "message": "sdasfd",
      "date": "13.12.2025 13:11:59",
      "isRead": false,
      "replies": []
    }
  ]
}